colourspace/__init__.py
colourspace/av/__init__.py
colourspace/av/container.py
colourspace/av/exception.py
colourspace/av/stream.py
colourspace/av/video.py
colourspace/av/filter/__init__.py
colourspace/av/filter/colourspace.py
colourspace/av/filter/correct.py
colourspace/av/filter/rotate.py
colourspace/frontend/__init__.py
colourspace/frontend/control/__init__.py
colourspace/frontend/control/video.py
colourspace/frontend/util/__init__.py
colourspace/frontend/util/drop.py
colourspace/frontend/util/pil.py
colourspace/frontend/viewer/__init__.py
colourspace/frontend/viewer/app.py
colourspace/frontend/window/__init__.py
colourspace/frontend/window/colourspace.py
colourspace/frontend/window/file.py
colourspace/frontend/window/metadata.py
colourspace/frontend/window/seek.py
colourspace/frontend/window/video.py
colourspace/util/__init__.py
colourspace/util/path.py
colourspace/util/settings.py
colourspace/util/time.py
colourspace-1.0.1.dist-info/LICENSE
colourspace-1.0.1.dist-info/METADATA
colourspace-1.0.1.dist-info/WHEEL
colourspace-1.0.1.dist-info/entry_points.txt
colourspace-1.0.1.dist-info/top_level.txt
colourspace-1.0.1.dist-info/RECORD
