Metadata-Version: 2.1
Name: colourspace
Version: 1.0.1
Summary: Render frames from videos and images applying the correct colourspace conversion.
Author-email: Svetlin Ankov <svetlin.ankov@live.com>, Simona Dimitrova <nimeria1308@gmail.com>
License: BSD 3-Clause License
Project-URL: Homepage, https://github.com/dumbledore/colourspace
Keywords: colourspace,colorspace,video,render
Classifier: License :: OSI Approved :: BSD License
Classifier: Programming Language :: Python
Classifier: Programming Language :: Python :: 3
Classifier: Intended Audience :: Science/Research
Classifier: Topic :: Desktop Environment
Classifier: Topic :: Multimedia :: Video :: Display
Classifier: Topic :: Scientific/Engineering :: Image Processing
Requires-Python: >=3.9
License-File: LICENSE
Requires-Dist: av >=10.0.0
Requires-Dist: pymediainfo >=6.0.1
Requires-Dist: wxPython >=4.2.0
Requires-Dist: Pillow >=9.0.1
Requires-Dist: pylru >=1.2.1
Provides-Extra: dev
Requires-Dist: autopep8 ; extra == 'dev'
Requires-Dist: pytest ; extra == 'dev'
